control_unit.v
module control_unit (
    input  wire [31:0] instr,     // lệnh hiện tại
    input  wire        br_eq,     // kết quả so sánh bằng
    input  wire        br_lt,     // kết quả so sánh nhỏ hơn

    output reg         pc_sel,    // chọn PC tiếp theo
    output reg  [2:0]  imm_sel,   // chọn loại immediate
    output reg         reg_wen,   // cho phép ghi thanh ghi
    output reg         br_un,     // so sánh branch unsigned hay signed
    output reg         b_sel,     // chọn ALU B = rs2 hay imm
    output reg         a_sel,     // chọn ALU A = rs1 hay PC
    output reg  [3:0]  alu_sel,   // chọn phép toán ALU
    output reg         mem_rw,    // ghi data memory
    output reg  [1:0]  wb_sel     // chọn dữ liệu ghi về RegFile
);

    // Tách các trường quan trọng của instruction
    wire [6:0] opcode = instr[6:0];
    wire [2:0] funct3 = instr[14:12];
    wire [6:0] funct7 = instr[31:25];

    // Mã chọn loại immediate
    localparam IMM_I = 3'b000;
    localparam IMM_S = 3'b001;
    localparam IMM_B = 3'b010;
    localparam IMM_U = 3'b011;
    localparam IMM_J = 3'b100;

    // Mã chọn ALU
    localparam ALU_ADD  = 4'b0000;
    localparam ALU_SUB  = 4'b0001;
    localparam ALU_AND  = 4'b0010;
    localparam ALU_OR   = 4'b0011;
    localparam ALU_XOR  = 4'b0100;
    localparam ALU_SLT  = 4'b0101;
    localparam ALU_SLTU = 4'b0110;
    localparam ALU_SLL  = 4'b0111;
    localparam ALU_SRL  = 4'b1000;
    localparam ALU_SRA  = 4'b1001;

    // Mã chọn write-back
    localparam WB_MEM = 2'b00;  // ghi dữ liệu từ memory
    localparam WB_ALU = 2'b01;  // ghi dữ liệu từ ALU
    localparam WB_PC4 = 2'b10;  // ghi PC + 4

    always @(*) begin
        // Giá trị mặc định để tránh latch
        pc_sel  = 1'b0;
        imm_sel = IMM_I;
        reg_wen = 1'b0;
        br_un   = 1'b0;
        b_sel   = 1'b0;
        a_sel   = 1'b0;
        alu_sel = ALU_ADD;
        mem_rw  = 1'b0;
        wb_sel  = WB_ALU;

        case (opcode)
            // R-type: add, sub, and, or, xor, slt,...
            7'b0110011: begin
                reg_wen = 1'b1;   // ghi kết quả về thanh ghi
                a_sel   = 1'b0;   // ALU A = rs1
                b_sel   = 1'b0;   // ALU B = rs2
                wb_sel  = WB_ALU; // dữ liệu ghi về lấy từ ALU

                case (funct3)
                    3'b000: alu_sel = (funct7 == 7'b0100000) ? ALU_SUB : ALU_ADD;
                    3'b111: alu_sel = ALU_AND;
                    3'b110: alu_sel = ALU_OR;
                    3'b100: alu_sel = ALU_XOR;
                    3'b010: alu_sel = ALU_SLT;
                    3'b011: alu_sel = ALU_SLTU;
                    3'b001: alu_sel = ALU_SLL;
                    3'b101: alu_sel = (funct7 == 7'b0100000) ? ALU_SRA : ALU_SRL;
                endcase
            end

            // I-type arithmetic: addi, andi, ori,...
            7'b0010011: begin
                reg_wen = 1'b1;
                imm_sel = IMM_I;
                a_sel   = 1'b0;   // ALU A = rs1
                b_sel   = 1'b1;   // ALU B = imm
                wb_sel  = WB_ALU;

                case (funct3)
                    3'b000: alu_sel = ALU_ADD;  // addi
                    3'b111: alu_sel = ALU_AND;  // andi
                    3'b110: alu_sel = ALU_OR;   // ori
                    3'b100: alu_sel = ALU_XOR;  // xori
                    3'b010: alu_sel = ALU_SLT;  // slti
                    3'b011: alu_sel = ALU_SLTU; // sltiu
                    3'b001: alu_sel = ALU_SLL;  // slli
                    3'b101: alu_sel = (funct7 == 7'b0100000) ? ALU_SRA : ALU_SRL;
                endcase
            end

            // Load: lw
            7'b0000011: begin
                reg_wen = 1'b1;
                imm_sel = IMM_I;
                a_sel   = 1'b0;   // A = rs1
                b_sel   = 1'b1;   // B = imm
                alu_sel = ALU_ADD; // địa chỉ = rs1 + imm
                wb_sel  = WB_MEM;  // ghi dữ liệu từ memory về thanh ghi
            end

            // Store: sw
            7'b0100011: begin
                imm_sel = IMM_S;
                a_sel   = 1'b0;   // A = rs1
                b_sel   = 1'b1;   // B = imm
                alu_sel = ALU_ADD; // địa chỉ = rs1 + imm
                mem_rw  = 1'b1;   // cho phép ghi memory
            end

            // Branch: beq, bne, blt, bge, bltu, bgeu
            7'b1100011: begin
                imm_sel = IMM_B;
                a_sel   = 1'b1;   // A = PC
                b_sel   = 1'b1;   // B = imm
                alu_sel = ALU_ADD; // target = PC + imm

                case (funct3)
                    3'b000: pc_sel = br_eq;            // beq
                    3'b001: pc_sel = ~br_eq;           // bne
                    3'b100: pc_sel = br_lt;            // blt
                    3'b101: pc_sel = br_eq | ~br_lt;   // bge
                    3'b110: begin
                        br_un = 1'b1;                  // unsigned
                        pc_sel = br_lt;                // bltu
                    end
                    3'b111: begin
                        br_un = 1'b1;                  // unsigned
                        pc_sel = br_eq | ~br_lt;       // bgeu
                    end
                endcase
            end

            // jal
            7'b1101111: begin
                reg_wen = 1'b1;
                imm_sel = IMM_J;
                a_sel   = 1'b1;   // A = PC
                b_sel   = 1'b1;   // B = imm
                alu_sel = ALU_ADD; // target = PC + imm
                wb_sel  = WB_PC4;  // rd = PC + 4
                pc_sel  = 1'b1;    // nhảy
            end

            // jalr
            7'b1100111: begin
                reg_wen = 1'b1;
                imm_sel = IMM_I;
                a_sel   = 1'b0;   // A = rs1
                b_sel   = 1'b1;   // B = imm
                alu_sel = ALU_ADD; // target = rs1 + imm
                wb_sel  = WB_PC4;  // rd = PC + 4
                pc_sel  = 1'b1;    // nhảy
            end

            // lui
            7'b0110111: begin
                reg_wen = 1'b1;
                imm_sel = IMM_U;
                a_sel   = 1'b0;
                b_sel   = 1'b1;
                alu_sel = ALU_ADD;
                wb_sel  = WB_ALU;
            end

            // auipc
            7'b0010111: begin
                reg_wen = 1'b1;
                imm_sel = IMM_U;
                a_sel   = 1'b1;   // A = PC
                b_sel   = 1'b1;   // B = imm
                alu_sel = ALU_ADD;
                wb_sel  = WB_ALU;
            end

        endcase
    end

endmodule


// Đây là bộ điều khiển
// Nhìn vào opcode, funct3, funct7 để quyết định:
// ALU làm gì
// lấy immediate kiểu nào
// có ghi thanh ghi không
// có ghi bộ nhớ không
// có nhảy hay không

control_unit_tb.v
`timescale 1ns/1ps

module control_unit_tb;
    reg  [31:0] instr;   // instruction đầu vào
    reg         br_eq;   // cờ so sánh bằng
    reg         br_lt;   // cờ so sánh nhỏ hơn

    wire        pc_sel;
    wire [2:0]  imm_sel;
    wire        reg_wen;
    wire        br_un;
    wire        b_sel;
    wire        a_sel;
    wire [3:0]  alu_sel;
    wire        mem_rw;
    wire [1:0]  wb_sel;

    // Gọi module control unit cần test
    control_unit dut (
        .instr(instr),
        .br_eq(br_eq),
        .br_lt(br_lt),
        .pc_sel(pc_sel),
        .imm_sel(imm_sel),
        .reg_wen(reg_wen),
        .br_un(br_un),
        .b_sel(b_sel),
        .a_sel(a_sel),
        .alu_sel(alu_sel),
        .mem_rw(mem_rw),
        .wb_sel(wb_sel)
    );

    initial begin
        $dumpfile("control_unit_tb.vcd");
        $dumpvars(0, control_unit_tb);

        // Mặc định
        br_eq = 0;
        br_lt = 0;

        // R-type add
        instr = 32'h002081B3;
        #10;
        $display("ADD  -> pc_sel=%b imm_sel=%b reg_wen=%b br_un=%b b_sel=%b a_sel=%b alu_sel=%b mem_rw=%b wb_sel=%b",
                 pc_sel, imm_sel, reg_wen, br_un, b_sel, a_sel, alu_sel, mem_rw, wb_sel);

        // R-type sub
        instr = 32'h402081B3;
        #10;
        $display("SUB  -> pc_sel=%b imm_sel=%b reg_wen=%b br_un=%b b_sel=%b a_sel=%b alu_sel=%b mem_rw=%b wb_sel=%b",
                 pc_sel, imm_sel, reg_wen, br_un, b_sel, a_sel, alu_sel, mem_rw, wb_sel);

        // addi
        instr = 32'h00500093;
        #10;
        $display("ADDI -> pc_sel=%b imm_sel=%b reg_wen=%b br_un=%b b_sel=%b a_sel=%b alu_sel=%b mem_rw=%b wb_sel=%b",
                 pc_sel, imm_sel, reg_wen, br_un, b_sel, a_sel, alu_sel, mem_rw, wb_sel);

        // lw
        instr = 32'h0000A103;
        #10;
        $display("LW   -> pc_sel=%b imm_sel=%b reg_wen=%b br_un=%b b_sel=%b a_sel=%b alu_sel=%b mem_rw=%b wb_sel=%b",
                 pc_sel, imm_sel, reg_wen, br_un, b_sel, a_sel, alu_sel, mem_rw, wb_sel);

        // sw
        instr = 32'h0020A223;
        #10;
        $display("SW   -> pc_sel=%b imm_sel=%b reg_wen=%b br_un=%b b_sel=%b a_sel=%b alu_sel=%b mem_rw=%b wb_sel=%b",
                 pc_sel, imm_sel, reg_wen, br_un, b_sel, a_sel, alu_sel, mem_rw, wb_sel);

        // beq khi điều kiện sai
        instr = 32'h00208463;
        br_eq = 0;
        br_lt = 0;
        #10;
        $display("BEQ false -> pc_sel=%b imm_sel=%b reg_wen=%b", pc_sel, imm_sel, reg_wen);

        // beq khi điều kiện đúng
        br_eq = 1;
        #10;
        $display("BEQ true  -> pc_sel=%b imm_sel=%b reg_wen=%b", pc_sel, imm_sel, reg_wen);

        // jal
        instr = 32'h0100006F;
        br_eq = 0;
        br_lt = 0;
        #10;
        $display("JAL  -> pc_sel=%b imm_sel=%b reg_wen=%b wb_sel=%b",
                 pc_sel, imm_sel, reg_wen, wb_sel);

        // jalr
        instr = 32'h00008067;
        #10;
        $display("JALR -> pc_sel=%b imm_sel=%b reg_wen=%b wb_sel=%b",
                 pc_sel, imm_sel, reg_wen, wb_sel);

        $finish;
    end

endmodule

control_unit_tb.vcd
$date
	Thu Apr 16 19:35:45 2026
$end
$version
	Icarus Verilog
$end
$timescale
	1ps
$end
$scope module control_unit_tb $end
$var wire 2 ! wb_sel [1:0] $end
$var wire 1 " reg_wen $end
$var wire 1 # pc_sel $end
$var wire 1 $ mem_rw $end
$var wire 3 % imm_sel [2:0] $end
$var wire 1 & br_un $end
$var wire 1 ' b_sel $end
$var wire 4 ( alu_sel [3:0] $end
$var wire 1 ) a_sel $end
$var reg 1 * br_eq $end
$var reg 1 + br_lt $end
$var reg 32 , instr [31:0] $end
$scope module dut $end
$var wire 1 * br_eq $end
$var wire 1 + br_lt $end
$var wire 32 - instr [31:0] $end
$var wire 7 . opcode [6:0] $end
$var wire 7 / funct7 [6:0] $end
$var wire 3 0 funct3 [2:0] $end
$var parameter 4 1 ALU_ADD $end
$var parameter 4 2 ALU_AND $end
$var parameter 4 3 ALU_OR $end
$var parameter 4 4 ALU_SLL $end
$var parameter 4 5 ALU_SLT $end
$var parameter 4 6 ALU_SLTU $end
$var parameter 4 7 ALU_SRA $end
$var parameter 4 8 ALU_SRL $end
$var parameter 4 9 ALU_SUB $end
$var parameter 4 : ALU_XOR $end
$var parameter 3 ; IMM_B $end
$var parameter 3 < IMM_I $end
$var parameter 3 = IMM_J $end
$var parameter 3 > IMM_S $end
$var parameter 3 ? IMM_U $end
$var parameter 2 @ WB_ALU $end
$var parameter 2 A WB_MEM $end
$var parameter 2 B WB_PC4 $end
$var reg 1 ) a_sel $end
$var reg 4 C alu_sel [3:0] $end
$var reg 1 ' b_sel $end
$var reg 1 & br_un $end
$var reg 3 D imm_sel [2:0] $end
$var reg 1 $ mem_rw $end
$var reg 1 # pc_sel $end
$var reg 1 " reg_wen $end
$var reg 2 E wb_sel [1:0] $end
$upscope $end
$upscope $end
$enddefinitions $end
$comment Show the parameter values. $end
$dumpall
b10 B
b0 A
b1 @
b11 ?
b1 >
b100 =
b0 <
b10 ;
b100 :
b1 9
b1000 8
b1001 7
b110 6
b101 5
b111 4
b11 3
b10 2
b0 1
$end
#0
$dumpvars
b1 E
b0 D
b0 C
b0 0
b0 /
b110011 .
b1000001000000110110011 -
b1000001000000110110011 ,
0+
0*
0)
b0 (
0'
0&
b0 %
0$
0#
1"
b1 !
$end
#10000
b1 (
b1 C
1"
b100000 /
b1000000001000001000000110110011 ,
b1000000001000001000000110110011 -
#20000
1'
b0 (
b0 C
1"
b10011 .
b0 /
b10100000000000010010011 ,
b10100000000000010010011 -
#30000
b0 !
b0 E
1'
1"
b11 .
b10 0
b1010000100000011 ,
b1010000100000011 -
#40000
1$
b1 %
b1 D
b1 !
b1 E
1'
0"
b100011 .
b1000001010001000100011 ,
b1000001010001000100011 -
#50000
1)
0$
1'
b10 %
b10 D
b1100011 .
b0 0
b1000001000010001100011 ,
b1000001000010001100011 -
#60000
1#
1)
1'
b10 %
b10 D
1*
#70000
b10 !
b10 E
1"
1)
1'
b100 %
b100 D
1#
b1101111 .
0*
b1000000000000000001101111 ,
b1000000000000000001101111 -
#80000
b10 !
b10 E
0)
1'
1"
b0 %
b0 D
1#
b1100111 .
b1000000001100111 ,
b1000000001100111 -
