alu.v
module alu (
    input  wire [31:0] a,
    input  wire [31:0] b,
    input  wire [3:0]  alu_sel,
    output reg  [31:0] y
);
    always @(*) begin
        case (alu_sel)
            4'b0000: y = a + b;                       // ADD
            4'b0001: y = a - b;                       // SUB
            4'b0010: y = a & b;                       // AND
            4'b0011: y = a | b;                       // OR
            4'b0100: y = a ^ b;                       // XOR
            4'b0101: y = ($signed(a) < $signed(b)) ? 32'd1 : 32'd0; // SLT
            4'b0110: y = (a < b) ? 32'd1 : 32'd0;     // SLTU
            4'b0111: y = a << b[4:0];                 // SLL
            4'b1000: y = a >> b[4:0];                 // SRL
            4'b1001: y = $signed(a) >>> b[4:0];       // SRA
            default: y = 32'b0;
        endcase
    end
endmodule

// b[4:0] vì shift amount chỉ cần 5 bit trong RV32
// >>> là arithmetic shift right

imm_gen.v
module imm_gen (
    input  wire [31:0] instr,    // lệnh 32-bit
    input  wire [2:0]  imm_sel,  // chọn loại immediate
    output reg  [31:0] imm       // immediate 32-bit sau khi mở rộng dấu
);

    always @(*) begin
        case (imm_sel)
            // I-type: addi, lw, jalr,...
            3'b000: imm = {{20{instr[31]}}, instr[31:20]};

            // S-type: sw
            3'b001: imm = {{20{instr[31]}}, instr[31:25], instr[11:7]};

            // B-type: beq, bne,...
            3'b010: imm = {{19{instr[31]}}, instr[31], instr[7],
                           instr[30:25], instr[11:8], 1'b0};

            // U-type: lui, auipc
            3'b011: imm = {instr[31:12], 12'b0};

            // J-type: jal
            3'b100: imm = {{11{instr[31]}}, instr[31], instr[19:12],
                           instr[20], instr[30:21], 1'b0};

            default: imm = 32'b0;
        endcase
    end

endmodule

// I-type: addi, lw, jalr
// S-type: sw
// B-type: beq, bne, blt...
// U-type: lui, auipc
// J-type: jal
// chuẩn theo format trong tài liệu (tr2)

control_unit.v
module control_unit (
    input  wire [31:0] instr,     // lệnh hiện tại
    input  wire        br_eq,     // kết quả so sánh bằng
    input  wire        br_lt,     // kết quả so sánh nhỏ hơn

    output reg         pc_sel,    // chọn PC tiếp theo
    output reg  [2:0]  imm_sel,   // chọn loại immediate
    output reg         reg_wen,   // cho phép ghi thanh ghi
    output reg         br_un,     // so sánh branch unsigned hay signed
    output reg         b_sel,     // chọn ALU B = rs2 hay imm
    output reg         a_sel,     // chọn ALU A = rs1 hay PC
    output reg  [3:0]  alu_sel,   // chọn phép toán ALU
    output reg         mem_rw,    // ghi data memory
    output reg  [1:0]  wb_sel     // chọn dữ liệu ghi về RegFile
);

    // Tách các trường quan trọng của instruction
    wire [6:0] opcode = instr[6:0];
    wire [2:0] funct3 = instr[14:12];
    wire [6:0] funct7 = instr[31:25];

    // Mã chọn loại immediate
    localparam IMM_I = 3'b000;
    localparam IMM_S = 3'b001;
    localparam IMM_B = 3'b010;
    localparam IMM_U = 3'b011;
    localparam IMM_J = 3'b100;

    // Mã chọn ALU
    localparam ALU_ADD  = 4'b0000;
    localparam ALU_SUB  = 4'b0001;
    localparam ALU_AND  = 4'b0010;
    localparam ALU_OR   = 4'b0011;
    localparam ALU_XOR  = 4'b0100;
    localparam ALU_SLT  = 4'b0101;
    localparam ALU_SLTU = 4'b0110;
    localparam ALU_SLL  = 4'b0111;
    localparam ALU_SRL  = 4'b1000;
    localparam ALU_SRA  = 4'b1001;

    // Mã chọn write-back
    localparam WB_MEM = 2'b00;  // ghi dữ liệu từ memory
    localparam WB_ALU = 2'b01;  // ghi dữ liệu từ ALU
    localparam WB_PC4 = 2'b10;  // ghi PC + 4

    always @(*) begin
        // Giá trị mặc định để tránh latch
        pc_sel  = 1'b0;
        imm_sel = IMM_I;
        reg_wen = 1'b0;
        br_un   = 1'b0;
        b_sel   = 1'b0;
        a_sel   = 1'b0;
        alu_sel = ALU_ADD;
        mem_rw  = 1'b0;
        wb_sel  = WB_ALU;

        case (opcode)
            // R-type: add, sub, and, or, xor, slt,...
            7'b0110011: begin
                reg_wen = 1'b1;   // ghi kết quả về thanh ghi
                a_sel   = 1'b0;   // ALU A = rs1
                b_sel   = 1'b0;   // ALU B = rs2
                wb_sel  = WB_ALU; // dữ liệu ghi về lấy từ ALU

                case (funct3)
                    3'b000: alu_sel = (funct7 == 7'b0100000) ? ALU_SUB : ALU_ADD;
                    3'b111: alu_sel = ALU_AND;
                    3'b110: alu_sel = ALU_OR;
                    3'b100: alu_sel = ALU_XOR;
                    3'b010: alu_sel = ALU_SLT;
                    3'b011: alu_sel = ALU_SLTU;
                    3'b001: alu_sel = ALU_SLL;
                    3'b101: alu_sel = (funct7 == 7'b0100000) ? ALU_SRA : ALU_SRL;
                endcase
            end

            // I-type arithmetic: addi, andi, ori,...
            7'b0010011: begin
                reg_wen = 1'b1;
                imm_sel = IMM_I;
                a_sel   = 1'b0;   // ALU A = rs1
                b_sel   = 1'b1;   // ALU B = imm
                wb_sel  = WB_ALU;

                case (funct3)
                    3'b000: alu_sel = ALU_ADD;  // addi
                    3'b111: alu_sel = ALU_AND;  // andi
                    3'b110: alu_sel = ALU_OR;   // ori
                    3'b100: alu_sel = ALU_XOR;  // xori
                    3'b010: alu_sel = ALU_SLT;  // slti
                    3'b011: alu_sel = ALU_SLTU; // sltiu
                    3'b001: alu_sel = ALU_SLL;  // slli
                    3'b101: alu_sel = (funct7 == 7'b0100000) ? ALU_SRA : ALU_SRL;
                endcase
            end

            // Load: lw
            7'b0000011: begin
                reg_wen = 1'b1;
                imm_sel = IMM_I;
                a_sel   = 1'b0;   // A = rs1
                b_sel   = 1'b1;   // B = imm
                alu_sel = ALU_ADD; // địa chỉ = rs1 + imm
                wb_sel  = WB_MEM;  // ghi dữ liệu từ memory về thanh ghi
            end

            // Store: sw
            7'b0100011: begin
                imm_sel = IMM_S;
                a_sel   = 1'b0;   // A = rs1
                b_sel   = 1'b1;   // B = imm
                alu_sel = ALU_ADD; // địa chỉ = rs1 + imm
                mem_rw  = 1'b1;   // cho phép ghi memory
            end

            // Branch: beq, bne, blt, bge, bltu, bgeu
            7'b1100011: begin
                imm_sel = IMM_B;
                a_sel   = 1'b1;   // A = PC
                b_sel   = 1'b1;   // B = imm
                alu_sel = ALU_ADD; // target = PC + imm

                case (funct3)
                    3'b000: pc_sel = br_eq;            // beq
                    3'b001: pc_sel = ~br_eq;           // bne
                    3'b100: pc_sel = br_lt;            // blt
                    3'b101: pc_sel = br_eq | ~br_lt;   // bge
                    3'b110: begin
                        br_un = 1'b1;                  // unsigned
                        pc_sel = br_lt;                // bltu
                    end
                    3'b111: begin
                        br_un = 1'b1;                  // unsigned
                        pc_sel = br_eq | ~br_lt;       // bgeu
                    end
                endcase
            end

            // jal
            7'b1101111: begin
                reg_wen = 1'b1;
                imm_sel = IMM_J;
                a_sel   = 1'b1;   // A = PC
                b_sel   = 1'b1;   // B = imm
                alu_sel = ALU_ADD; // target = PC + imm
                wb_sel  = WB_PC4;  // rd = PC + 4
                pc_sel  = 1'b1;    // nhảy
            end

            // jalr
            7'b1100111: begin
                reg_wen = 1'b1;
                imm_sel = IMM_I;
                a_sel   = 1'b0;   // A = rs1
                b_sel   = 1'b1;   // B = imm
                alu_sel = ALU_ADD; // target = rs1 + imm
                wb_sel  = WB_PC4;  // rd = PC + 4
                pc_sel  = 1'b1;    // nhảy
            end

            // lui
            7'b0110111: begin
                reg_wen = 1'b1;
                imm_sel = IMM_U;
                a_sel   = 1'b0;
                b_sel   = 1'b1;
                alu_sel = ALU_ADD;
                wb_sel  = WB_ALU;
            end

            // auipc
            7'b0010111: begin
                reg_wen = 1'b1;
                imm_sel = IMM_U;
                a_sel   = 1'b1;   // A = PC
                b_sel   = 1'b1;   // B = imm
                alu_sel = ALU_ADD;
                wb_sel  = WB_ALU;
            end

        endcase
    end

endmodule


// Đây là bộ điều khiển
// Nhìn vào opcode, funct3, funct7 để quyết định:
// ALU làm gì
// lấy immediate kiểu nào
// có ghi thanh ghi không
// có ghi bộ nhớ không
// có nhảy hay không

instruction_test_tb.v
`timescale 1ns/1ps

module instruction_test_tb;

    // Đầu vào test 
    reg  [31:0] instr;      // instruction đang test
    reg         br_eq;      // cờ branch equal
    reg         br_lt;      // cờ branch less than

    reg  [31:0] rs1_data;   // dữ liệu giả lập từ rs1
    reg  [31:0] rs2_data;   // dữ liệu giả lập từ rs2
    reg  [31:0] pc;         // PC giả lập

    // Đầu ra từ control unit 
    wire        pc_sel;
    wire [2:0]  imm_sel;
    wire        reg_wen;
    wire        br_un;
    wire        b_sel;
    wire        a_sel;
    wire [3:0]  alu_sel;
    wire        mem_rw;
    wire [1:0]  wb_sel;

    // Đầu ra từ imm_gen 
    wire [31:0] imm;

    // Tách trường thanh ghi 
    wire [4:0] rs1 = instr[19:15];
    wire [4:0] rs2 = instr[24:20];
    wire [4:0] rd  = instr[11:7];

    // Đầu vào/ra ALU 
    wire [31:0] alu_a;
    wire [31:0] alu_b;
    wire [31:0] alu_y;

    // Dữ liệu write-back mô phỏng 
    reg  [31:0] mem_data;
    wire [31:0] wb_data;

    // DUTs 
    control_unit U_CTRL (
        .instr(instr),
        .br_eq(br_eq),
        .br_lt(br_lt),
        .pc_sel(pc_sel),
        .imm_sel(imm_sel),
        .reg_wen(reg_wen),
        .br_un(br_un),
        .b_sel(b_sel),
        .a_sel(a_sel),
        .alu_sel(alu_sel),
        .mem_rw(mem_rw),
        .wb_sel(wb_sel)
    );

    imm_gen U_IMM (
        .instr(instr),
        .imm_sel(imm_sel),
        .imm(imm)
    );

    // a_sel = 0 -> ALU A = rs1_data
    // a_sel = 1 -> ALU A = pc
    assign alu_a = (a_sel) ? pc : rs1_data;

    // b_sel = 0 -> ALU B = rs2_data
    // b_sel = 1 -> ALU B = imm
    assign alu_b = (b_sel) ? imm : rs2_data;

    alu U_ALU (
        .a(alu_a),
        .b(alu_b),
        .alu_sel(alu_sel),
        .y(alu_y)
    );

    // wb_sel:
    // 00 = memory
    // 01 = ALU
    // 10 = PC + 4
    assign wb_data = (wb_sel == 2'b00) ? mem_data :
                     (wb_sel == 2'b01) ? alu_y    :
                     (wb_sel == 2'b10) ? (pc + 32'd4) :
                     32'b0;

    task show_case;
        input [255:0] name;
        begin
            $display("\n==============================");
            $display("TEST: %0s", name);
            $display("==============================");
        end
    endtask

    // ===== Task in trạng thái chung =====
    task show_signals;
        begin
            $display("instr    = %h", instr);
            $display("rs1=%0d rs2=%0d rd=%0d", rs1, rs2, rd);
            $display("pc_sel   = %b", pc_sel);
            $display("imm_sel  = %b", imm_sel);
            $display("imm      = %0d (0x%h)", $signed(imm), imm);
            $display("reg_wen  = %b", reg_wen);
            $display("br_un    = %b", br_un);
            $display("a_sel    = %b", a_sel);
            $display("b_sel    = %b", b_sel);
            $display("alu_sel  = %b", alu_sel);
            $display("mem_rw   = %b", mem_rw);
            $display("wb_sel   = %b", wb_sel);
            $display("alu_a    = %0d", $signed(alu_a));
            $display("alu_b    = %0d", $signed(alu_b));
            $display("alu_y    = %0d", $signed(alu_y));
            $display("wb_data  = %0d", $signed(wb_data));
        end
    endtask

    initial begin
        $dumpfile("instruction_test_tb.vcd");
        $dumpvars(0, instruction_test_tb);

        // Giá trị mặc định
        instr    = 32'b0;
        br_eq    = 1'b0;
        br_lt    = 1'b0;
        rs1_data = 32'b0;
        rs2_data = 32'b0;
        pc       = 32'd100;   // chọn PC mẫu
        mem_data = 32'd123;   // dữ liệu memory mẫu cho lệnh lw

        // ADDI: addi x1, x0, 5
        show_case("ADDI x1, x0, 5");
        instr    = 32'h00500093;
        rs1_data = 32'd0;
        rs2_data = 32'd0;
        br_eq    = 1'b0;
        br_lt    = 1'b0;
        #10;
        show_signals;
        if (imm == 32'd5 && alu_y == 32'd5 && reg_wen == 1'b1 && wb_sel == 2'b01)
            $display("PASS");
        else
            $display("FAIL");

        // ADD: add x3, x1, x2
        show_case("ADD x3, x1, x2");
        instr    = 32'h002081B3;
        rs1_data = 32'd10;
        rs2_data = 32'd7;
        #10;
        show_signals;
        if (alu_y == 32'd17 && reg_wen == 1'b1 && alu_sel == 4'b0000)
            $display("PASS");
        else
            $display("FAIL");

        // SUB: sub x4, x2, x1
        show_case("SUB x4, x2, x1");
        instr    = 32'h40110233;
        rs1_data = 32'd9;
        rs2_data = 32'd4;
        #10;
        show_signals;
        if (alu_y == 32'd5 && reg_wen == 1'b1 && alu_sel == 4'b0001)
            $display("PASS");
        else
            $display("FAIL");

        // AND: and x5, x1, x2
        show_case("AND x5, x1, x2");
        instr    = 32'h0020F2B3;
        rs1_data = 32'h0000000F;
        rs2_data = 32'h0000000A;
        #10;
        show_signals;
        if (alu_y == 32'h0000000A && alu_sel == 4'b0010)
            $display("PASS");
        else
            $display("FAIL");

        // LW: lw x2, 0(x1)
        show_case("LW x2, 0(x1)");
        instr    = 32'h0000A103;
        rs1_data = 32'd20;
        mem_data = 32'd55;
        #10;
        show_signals;
        if (imm == 32'd0 && alu_y == 32'd20 && reg_wen == 1'b1 && wb_sel == 2'b00 && mem_rw == 1'b0)
            $display("PASS");
        else
            $display("FAIL");

        // SW: sw x2, 4(x1)
        show_case("SW x2, 4(x1)");
        instr    = 32'h0020A223;
        rs1_data = 32'd20;
        rs2_data = 32'd99;
        #10;
        show_signals;
        if (imm == 32'd4 && alu_y == 32'd24 && reg_wen == 1'b0 && mem_rw == 1'b1)
            $display("PASS");
        else
            $display("FAIL");


        // BEQ false: beq x1, x2, 8
        show_case("BEQ false");
        instr    = 32'h00208463;
        rs1_data = 32'd5;
        rs2_data = 32'd7;
        br_eq    = 1'b0;
        br_lt    = 1'b1;
        #10;
        show_signals;
        if (pc_sel == 1'b0 && imm == 32'd8)
            $display("PASS");
        else
            $display("FAIL");

        // 8) BEQ true
        show_case("BEQ true");
        instr    = 32'h00208463;
        br_eq    = 1'b1;
        br_lt    = 1'b0;
        #10;
        show_signals;
        if (pc_sel == 1'b1 && alu_y == pc + 32'd8)
            $display("PASS");
        else
            $display("FAIL");

        // JAL: jal x0, 16
        show_case("JAL x0, 16");
        instr    = 32'h0100006F;
        br_eq    = 1'b0;
        br_lt    = 1'b0;
        pc       = 32'd100;
        #10;
        show_signals;
        if (pc_sel == 1'b1 && imm == 32'd16 && wb_sel == 2'b10 && wb_data == 32'd104)
            $display("PASS");
        else
            $display("FAIL");

        // JALR: jalr x0, 0(x1)
        show_case("JALR x0, 0(x1)");
        instr    = 32'h00008067;
        rs1_data = 32'd200;
        pc       = 32'd100;
        #10;
        show_signals;
        if (pc_sel == 1'b1 && imm == 32'd0 && alu_y == 32'd200 && wb_sel == 2'b10 && wb_data == 32'd104)
            $display("PASS");
        else
            $display("FAIL");

        // LUI: lui x5, 0x12345
        show_case("LUI x5, 0x12345");
        instr    = 32'h123452B7;
        rs1_data = 32'd0;
        #10;
        show_signals;
        if (imm == 32'h12345000 && reg_wen == 1'b1)
            $display("PASS");
        else
            $display("FAIL");

        // AUIPC: auipc x5, 0x12345
        show_case("AUIPC x5, 0x12345");
        instr    = 32'h12345297;
        pc       = 32'd100;
        #10;
        show_signals;
        if (imm == 32'h12345000 && alu_y == (32'h12345000 + 32'd100))
            $display("PASS");
        else
            $display("FAIL");

        $display("\n=== KET THUC TEST TONG HOP CAC LOAI LENH ===");
        $finish;
    end

endmodule

instruction_test_tb.vcd
$date
	Thu Apr 16 21:18:42 2026
$end
$version
	Icarus Verilog
$end
$timescale
	1ps
$end
$scope module instruction_test_tb $end
$var wire 2 ! wb_sel [1:0] $end
$var wire 32 " wb_data [31:0] $end
$var wire 5 # rs2 [4:0] $end
$var wire 5 $ rs1 [4:0] $end
$var wire 1 % reg_wen $end
$var wire 5 & rd [4:0] $end
$var wire 1 ' pc_sel $end
$var wire 1 ( mem_rw $end
$var wire 3 ) imm_sel [2:0] $end
$var wire 32 * imm [31:0] $end
$var wire 1 + br_un $end
$var wire 1 , b_sel $end
$var wire 32 - alu_y [31:0] $end
$var wire 4 . alu_sel [3:0] $end
$var wire 32 / alu_b [31:0] $end
$var wire 32 0 alu_a [31:0] $end
$var wire 1 1 a_sel $end
$var reg 1 2 br_eq $end
$var reg 1 3 br_lt $end
$var reg 32 4 instr [31:0] $end
$var reg 32 5 mem_data [31:0] $end
$var reg 32 6 pc [31:0] $end
$var reg 32 7 rs1_data [31:0] $end
$var reg 32 8 rs2_data [31:0] $end
$scope module U_ALU $end
$var wire 32 9 a [31:0] $end
$var wire 32 : b [31:0] $end
$var wire 4 ; alu_sel [3:0] $end
$var reg 32 < y [31:0] $end
$upscope $end
$scope module U_CTRL $end
$var wire 1 2 br_eq $end
$var wire 1 3 br_lt $end
$var wire 32 = instr [31:0] $end
$var wire 7 > opcode [6:0] $end
$var wire 7 ? funct7 [6:0] $end
$var wire 3 @ funct3 [2:0] $end
$var parameter 4 A ALU_ADD $end
$var parameter 4 B ALU_AND $end
$var parameter 4 C ALU_OR $end
$var parameter 4 D ALU_SLL $end
$var parameter 4 E ALU_SLT $end
$var parameter 4 F ALU_SLTU $end
$var parameter 4 G ALU_SRA $end
$var parameter 4 H ALU_SRL $end
$var parameter 4 I ALU_SUB $end
$var parameter 4 J ALU_XOR $end
$var parameter 3 K IMM_B $end
$var parameter 3 L IMM_I $end
$var parameter 3 M IMM_J $end
$var parameter 3 N IMM_S $end
$var parameter 3 O IMM_U $end
$var parameter 2 P WB_ALU $end
$var parameter 2 Q WB_MEM $end
$var parameter 2 R WB_PC4 $end
$var reg 1 1 a_sel $end
$var reg 4 S alu_sel [3:0] $end
$var reg 1 , b_sel $end
$var reg 1 + br_un $end
$var reg 3 T imm_sel [2:0] $end
$var reg 1 ( mem_rw $end
$var reg 1 ' pc_sel $end
$var reg 1 % reg_wen $end
$var reg 2 U wb_sel [1:0] $end
$upscope $end
$scope module U_IMM $end
$var wire 3 V imm_sel [2:0] $end
$var wire 32 W instr [31:0] $end
$var reg 32 X imm [31:0] $end
$upscope $end
$scope task show_case $end
$var reg 256 Y name [255:0] $end
$upscope $end
$scope task show_signals $end
$upscope $end
$upscope $end
$enddefinitions $end
$comment Show the parameter values. $end
$dumpall
b10 R
b0 Q
b1 P
b11 O
b1 N
b100 M
b0 L
b10 K
b100 J
b1 I
b1000 H
b1001 G
b110 F
b101 E
b111 D
b11 C
b10 B
b0 A
$end
#0
$dumpvars
b100000101000100010001000100100100100000011110000011000100101100001000000111100000110000001011000010000000110101 Y
b101 X
b10100000000000010010011 W
b0 V
b1 U
b0 T
b0 S
b0 @
b0 ?
b10011 >
b10100000000000010010011 =
b101 <
b0 ;
b101 :
b0 9
b0 8
b0 7
b1100100 6
b1111011 5
b10100000000000010010011 4
03
02
01
b0 0
b101 /
b0 .
b101 -
1,
0+
b101 *
b0 )
0(
0'
b1 &
1%
b0 $
b101 #
b101 "
b1 !
$end
#10000
b10001 "
b10001 -
b10001 <
0,
1%
b111 /
b111 :
b1010 0
b1010 9
b1 $
b10 #
b11 &
b110011 >
b10 *
b10 X
b111 8
b1010 7
b1000001000000110110011 4
b1000001000000110110011 =
b1000001000000110110011 W
b100000101000100010001000010000001111000001100110010110000100000011110000011000100101100001000000111100000110010 Y
#20000
b101 "
b101 -
b101 <
b1 .
b1 ;
b1 S
1%
b100 /
b100 :
b1001 0
b1001 9
b10 $
b1 #
b100 &
b100000 ?
b10000000001 *
b10000000001 X
b100 8
b1001 7
b1000000000100010000001000110011 4
b1000000000100010000001000110011 =
b1000000000100010000001000110011 W
b101001101010101010000100010000001111000001101000010110000100000011110000011001000101100001000000111100000110001 Y
#30000
b1010 "
b1010 -
b1010 <
b10 .
b10 ;
b10 S
1%
b1010 /
b1010 :
b1111 0
b1111 9
b1 $
b10 #
b101 &
b111 @
b0 ?
b10 *
b10 X
b1010 8
b1111 7
b1000001111001010110011 4
b1000001111001010110011 =
b1000001111001010110011 W
b100000101001110010001000010000001111000001101010010110000100000011110000011000100101100001000000111100000110010 Y
#40000
b110111 "
b0 /
b0 :
b10100 -
b10100 <
b0 !
b0 U
1,
b0 .
b0 ;
b0 S
1%
b10100 0
b10100 9
b0 #
b10 &
b11 >
b10 @
b0 *
b0 X
b110111 5
b10100 7
b1010000100000011 4
b1010000100000011 =
b1010000100000011 W
b10011000101011100100000011110000011001000101100001000000011000000101000011110000011000100101001 Y
#50000
b11000 "
b11000 -
b11000 <
1(
b1 )
b1 T
b1 V
b1 !
b1 U
1,
0%
b100 /
b100 :
b10 #
b100 &
b100011 >
b100 *
b100 X
b1100011 8
b1000001010001000100011 4
b1000001010001000100011 =
b1000001010001000100011 W
b10100110101011100100000011110000011001000101100001000000011010000101000011110000011000100101001 Y
#60000
b1101100 "
b1101100 -
b1101100 <
b1000 /
b1000 :
11
0(
1,
b10 )
b10 T
b10 V
b1100100 0
b1100100 9
b1000 &
b1100011 >
b0 @
b1000 *
b1000 X
13
b111 8
b101 7
b1000001000010001100011 4
b1000001000010001100011 =
b1000001000010001100011 W
b10000100100010101010001001000000110011001100001011011000111001101100101 Y
#70000
1'
11
1,
b10 )
b10 T
b10 V
03
12
b100001001000101010100010010000001110100011100100111010101100101 Y
#80000
b1101000 "
b1110100 -
b1110100 <
b10000 /
b10000 :
b10 !
b10 U
1%
11
1,
b100 )
b100 T
b100 V
1'
b0 $
b10000 #
b0 &
b1101111 >
b10000 *
b10000 X
02
b1000000000000000001101111 4
b1000000000000000001101111 =
b1000000000000000001101111 W
b1001010010000010100110000100000011110000011000000101100001000000011000100110110 Y
#90000
b11001000 0
b11001000 9
b11001000 -
b11001000 <
b10 !
b10 U
01
1,
1%
b0 )
b0 T
b0 V
1'
b0 /
b0 :
b1 $
b0 #
b1100111 >
b0 *
b0 X
b11001000 7
b1000000001100111 4
b1000000001100111 =
b1000000001100111 W
b100101001000001010011000101001000100000011110000011000000101100001000000011000000101000011110000011000100101001 Y
#100000
b10010001101000101000000000000 "
b10010001101000101000000000000 -
b10010001101000101000000000000 <
b11 )
b11 T
b11 V
b1 !
b1 U
1,
1%
0'
b10010001101000101000000000000 /
b10010001101000101000000000000 :
b0 0
b0 9
b1000 $
b11 #
b101 &
b110111 >
b101 @
b1001 ?
b10010001101000101000000000000 *
b10010001101000101000000000000 X
b0 7
b10010001101000101001010110111 4
b10010001101000101001010110111 =
b10010001101000101001010110111 W
b10011000101010101001001001000000111100000110101001011000010000000110000011110000011000100110010001100110011010000110101 Y
#110000
b10010001101000101000001100100 "
b10010001101000101000001100100 -
b10010001101000101000001100100 <
b1100100 0
b1100100 9
11
1,
1%
b11 )
b11 T
b11 V
b10111 >
b10010001101000101001010010111 4
b10010001101000101001010010111 =
b10010001101000101001010010111 W
b100000101010101010010010101000001000011001000000111100000110101001011000010000000110000011110000011000100110010001100110011010000110101 Y
