dmem.v
module dmem (
    input  wire        clk,    // clock
    input  wire        we,     // write enable: cho phép ghi
    input  wire [31:0] addr,   // địa chỉ bộ nhớ dữ liệu
    input  wire [31:0] wdata,  // dữ liệu ghi vào bộ nhớ
    output wire [31:0] rdata   // dữ liệu đọc ra từ bộ nhớ
);

    // Bộ nhớ dữ liệu 256 word
    reg [31:0] mem [0:255];

    // Đọc dữ liệu kiểu combinational
    assign rdata = mem[addr[31:2]];

    // Ghi dữ liệu ở cạnh lên clock khi we = 1
    always @(posedge clk) begin
        if (we)
            mem[addr[31:2]] <= wdata;
    end

endmodule

// Dùng cho lw, sw
// we = 1 thì ghi dữ liệu vào DMEM
// we = 0 thì chỉ đọc
// we là write enable
// đọc dữ liệu kiểu combinational

alu.v
module alu (
    input  wire [31:0] a,        // toán hạng A
    input  wire [31:0] b,        // toán hạng B
    input  wire [3:0]  alu_sel,  // tín hiệu chọn phép toán
    output reg  [31:0] y         // kết quả ALU
);

    always @(*) begin
        case (alu_sel)
            4'b0000: y = a + b;                              // ADD
            4'b0001: y = a - b;                              // SUB
            4'b0010: y = a & b;                              // AND
            4'b0011: y = a | b;                              // OR
            4'b0100: y = a ^ b;                              // XOR
            4'b0101: y = ($signed(a) < $signed(b)) ? 32'd1 : 32'd0; // SLT
            4'b0110: y = (a < b) ? 32'd1 : 32'd0;            // SLTU
            4'b0111: y = a << b[4:0];                        // SLL
            4'b1000: y = a >> b[4:0];                        // SRL
            4'b1001: y = $signed(a) >>> b[4:0];              // SRA
            default: y = 32'b0;
        endcase
    end

endmodule

// b[4:0] vì shift amount chỉ cần 5 bit trong RV32
// >>> là arithmetic shift right

control_unit.v
module control_unit (
    input  wire [31:0] instr,     // lệnh hiện tại
    input  wire        br_eq,     // kết quả so sánh bằng
    input  wire        br_lt,     // kết quả so sánh nhỏ hơn

    output reg         pc_sel,    // chọn PC tiếp theo
    output reg  [2:0]  imm_sel,   // chọn loại immediate
    output reg         reg_wen,   // cho phép ghi thanh ghi
    output reg         br_un,     // so sánh branch unsigned hay signed
    output reg         b_sel,     // chọn ALU B = rs2 hay imm
    output reg         a_sel,     // chọn ALU A = rs1 hay PC
    output reg  [3:0]  alu_sel,   // chọn phép toán ALU
    output reg         mem_rw,    // ghi data memory
    output reg  [1:0]  wb_sel     // chọn dữ liệu ghi về RegFile
);

    // Tách các trường quan trọng của instruction
    wire [6:0] opcode = instr[6:0];
    wire [2:0] funct3 = instr[14:12];
    wire [6:0] funct7 = instr[31:25];

    // Mã chọn loại immediate
    localparam IMM_I = 3'b000;
    localparam IMM_S = 3'b001;
    localparam IMM_B = 3'b010;
    localparam IMM_U = 3'b011;
    localparam IMM_J = 3'b100;

    // Mã chọn ALU
    localparam ALU_ADD  = 4'b0000;
    localparam ALU_SUB  = 4'b0001;
    localparam ALU_AND  = 4'b0010;
    localparam ALU_OR   = 4'b0011;
    localparam ALU_XOR  = 4'b0100;
    localparam ALU_SLT  = 4'b0101;
    localparam ALU_SLTU = 4'b0110;
    localparam ALU_SLL  = 4'b0111;
    localparam ALU_SRL  = 4'b1000;
    localparam ALU_SRA  = 4'b1001;

    // Mã chọn write-back
    localparam WB_MEM = 2'b00;  // ghi dữ liệu từ memory
    localparam WB_ALU = 2'b01;  // ghi dữ liệu từ ALU
    localparam WB_PC4 = 2'b10;  // ghi PC + 4

    always @(*) begin
        // Giá trị mặc định để tránh latch
        pc_sel  = 1'b0;
        imm_sel = IMM_I;
        reg_wen = 1'b0;
        br_un   = 1'b0;
        b_sel   = 1'b0;
        a_sel   = 1'b0;
        alu_sel = ALU_ADD;
        mem_rw  = 1'b0;
        wb_sel  = WB_ALU;

        case (opcode)

            // =====================
            // R-type: add, sub, and, or, xor, slt,...
            // =====================
            7'b0110011: begin
                reg_wen = 1'b1;   // ghi kết quả về thanh ghi
                a_sel   = 1'b0;   // ALU A = rs1
                b_sel   = 1'b0;   // ALU B = rs2
                wb_sel  = WB_ALU; // dữ liệu ghi về lấy từ ALU

                case (funct3)
                    3'b000: alu_sel = (funct7 == 7'b0100000) ? ALU_SUB : ALU_ADD;
                    3'b111: alu_sel = ALU_AND;
                    3'b110: alu_sel = ALU_OR;
                    3'b100: alu_sel = ALU_XOR;
                    3'b010: alu_sel = ALU_SLT;
                    3'b011: alu_sel = ALU_SLTU;
                    3'b001: alu_sel = ALU_SLL;
                    3'b101: alu_sel = (funct7 == 7'b0100000) ? ALU_SRA : ALU_SRL;
                endcase
            end

            // =====================
            // I-type arithmetic: addi, andi, ori,...
            // =====================
            7'b0010011: begin
                reg_wen = 1'b1;
                imm_sel = IMM_I;
                a_sel   = 1'b0;   // ALU A = rs1
                b_sel   = 1'b1;   // ALU B = imm
                wb_sel  = WB_ALU;

                case (funct3)
                    3'b000: alu_sel = ALU_ADD;  // addi
                    3'b111: alu_sel = ALU_AND;  // andi
                    3'b110: alu_sel = ALU_OR;   // ori
                    3'b100: alu_sel = ALU_XOR;  // xori
                    3'b010: alu_sel = ALU_SLT;  // slti
                    3'b011: alu_sel = ALU_SLTU; // sltiu
                    3'b001: alu_sel = ALU_SLL;  // slli
                    3'b101: alu_sel = (funct7 == 7'b0100000) ? ALU_SRA : ALU_SRL;
                endcase
            end

            // =====================
            // Load: lw
            // =====================
            7'b0000011: begin
                reg_wen = 1'b1;
                imm_sel = IMM_I;
                a_sel   = 1'b0;   // A = rs1
                b_sel   = 1'b1;   // B = imm
                alu_sel = ALU_ADD; // địa chỉ = rs1 + imm
                wb_sel  = WB_MEM;  // ghi dữ liệu từ memory về thanh ghi
            end

            // =====================
            // Store: sw
            // =====================
            7'b0100011: begin
                imm_sel = IMM_S;
                a_sel   = 1'b0;   // A = rs1
                b_sel   = 1'b1;   // B = imm
                alu_sel = ALU_ADD; // địa chỉ = rs1 + imm
                mem_rw  = 1'b1;   // cho phép ghi memory
            end

            // =====================
            // Branch: beq, bne, blt, bge, bltu, bgeu
            // =====================
            7'b1100011: begin
                imm_sel = IMM_B;
                a_sel   = 1'b1;   // A = PC
                b_sel   = 1'b1;   // B = imm
                alu_sel = ALU_ADD; // target = PC + imm

                case (funct3)
                    3'b000: pc_sel = br_eq;            // beq
                    3'b001: pc_sel = ~br_eq;           // bne
                    3'b100: pc_sel = br_lt;            // blt
                    3'b101: pc_sel = br_eq | ~br_lt;   // bge
                    3'b110: begin
                        br_un = 1'b1;                  // unsigned
                        pc_sel = br_lt;                // bltu
                    end
                    3'b111: begin
                        br_un = 1'b1;                  // unsigned
                        pc_sel = br_eq | ~br_lt;       // bgeu
                    end
                endcase
            end

            // =====================
            // jal
            // =====================
            7'b1101111: begin
                reg_wen = 1'b1;
                imm_sel = IMM_J;
                a_sel   = 1'b1;   // A = PC
                b_sel   = 1'b1;   // B = imm
                alu_sel = ALU_ADD; // target = PC + imm
                wb_sel  = WB_PC4;  // rd = PC + 4
                pc_sel  = 1'b1;    // nhảy
            end

            // =====================
            // jalr
            // =====================
            7'b1100111: begin
                reg_wen = 1'b1;
                imm_sel = IMM_I;
                a_sel   = 1'b0;   // A = rs1
                b_sel   = 1'b1;   // B = imm
                alu_sel = ALU_ADD; // target = rs1 + imm
                wb_sel  = WB_PC4;  // rd = PC + 4
                pc_sel  = 1'b1;    // nhảy
            end

            // =====================
            // lui
            // =====================
            7'b0110111: begin
                reg_wen = 1'b1;
                imm_sel = IMM_U;
                a_sel   = 1'b0;
                b_sel   = 1'b1;
                alu_sel = ALU_ADD;
                wb_sel  = WB_ALU;
            end

            // =====================
            // auipc
            // =====================
            7'b0010111: begin
                reg_wen = 1'b1;
                imm_sel = IMM_U;
                a_sel   = 1'b1;   // A = PC
                b_sel   = 1'b1;   // B = imm
                alu_sel = ALU_ADD;
                wb_sel  = WB_ALU;
            end

        endcase
    end

endmodule


// Đây là bộ điều khiển
// Nhìn vào opcode, funct3, funct7 để quyết định:
// ALU làm gì
// lấy immediate kiểu nào
// có ghi thanh ghi không
// có ghi bộ nhớ không
// có nhảy hay không

branch_comp.v
module branch_comp (
    input  wire [31:0] a,      // toán hạng 1
    input  wire [31:0] b,      // toán hạng 2
    input  wire        br_un,  // 1: so sánh unsigned, 0: so sánh signed
    output wire        br_eq,  // bằng nhau hay không
    output wire        br_lt   // a < b hay không
);

    // So sánh bằng nhau
    assign br_eq = (a == b);

    // So sánh nhỏ hơn
    // Nếu br_un = 1 thì so sánh unsigned
    // Nếu br_un = 0 thì so sánh signed
    assign br_lt = br_un ? (a < b) : ($signed(a) < $signed(b));

endmodule

// br_eq: hai thanh ghi có bằng nhau không
// br_lt: nhỏ hơn
// br_un = 1 thì so sánh unsigned
// br_un = 0 thì so sánh signed

imm_gen.v
module imm_gen (
    input  wire [31:0] instr,    // lệnh 32-bit
    input  wire [2:0]  imm_sel,  // chọn loại immediate
    output reg  [31:0] imm       // immediate 32-bit sau khi mở rộng dấu
);

    always @(*) begin
        case (imm_sel)
            // I-type: addi, lw, jalr,...
            3'b000: imm = {{20{instr[31]}}, instr[31:20]};

            // S-type: sw
            3'b001: imm = {{20{instr[31]}}, instr[31:25], instr[11:7]};

            // B-type: beq, bne,...
            3'b010: imm = {{19{instr[31]}}, instr[31], instr[7],
                           instr[30:25], instr[11:8], 1'b0};

            // U-type: lui, auipc
            3'b011: imm = {instr[31:12], 12'b0};

            // J-type: jal
            3'b100: imm = {{11{instr[31]}}, instr[31], instr[19:12],
                           instr[20], instr[30:21], 1'b0};

            default: imm = 32'b0;
        endcase
    end

endmodule

// I-type: addi, lw, jalr
// S-type: sw
// B-type: beq, bne, blt...
// U-type: lui, auipc
// J-type: jal
// chuẩn theo format trong tài liệu (tr2)

reg_file.v
module reg_file (
    input  wire        clk,   // clock
    input  wire        we,    // write enable
    input  wire [4:0]  rs1,   // địa chỉ thanh ghi nguồn 1
    input  wire [4:0]  rs2,   // địa chỉ thanh ghi nguồn 2
    input  wire [4:0]  rd,    // địa chỉ thanh ghi đích
    input  wire [31:0] wd,    // dữ liệu ghi vào rd
    output wire [31:0] rd1,   // dữ liệu đọc từ rs1
    output wire [31:0] rd2    // dữ liệu đọc từ rs2
);

    // 32 thanh ghi, mỗi thanh ghi 32 bit
    reg [31:0] regs [0:31];
    integer i;

    // Khởi tạo tất cả thanh ghi về 0 khi bắt đầu mô phỏng
    initial begin
        for (i = 0; i < 32; i = i + 1)
            regs[i] = 32'b0;
    end

    // x0 luôn bằng 0 nên nếu đọc rs1/rs2 = 0 thì trả về 0
    assign rd1 = (rs1 == 5'd0) ? 32'b0 : regs[rs1];
    assign rd2 = (rs2 == 5'd0) ? 32'b0 : regs[rs2];

    // Ghi dữ liệu vào rd ở cạnh lên clock nếu we = 1
    // Không cho phép ghi vào x0
    always @(posedge clk) begin
        if (we && rd != 5'd0)
            regs[rd] <= wd;
    end

endmodule

// Có 32 thanh ghi
// x0 luôn bằng 0 nên:
// đọc x0 trả về 0
// không cho ghi vào rd = 0

imem.v
module imem (
    input  wire [31:0] addr,   // địa chỉ đọc lệnh, thường là PC
    output wire [31:0] instr   // lệnh 32-bit đọc ra
);

    // Bộ nhớ lệnh gồm 256 word, mỗi word 32 bit
    reg [31:0] mem [0:255];

    initial begin
        // Đọc nội dung chương trình từ file imem.hex
        $readmemh("imem.hex", mem);
    end

    // Vì mỗi lệnh dài 4 byte nên dùng addr[31:2]
    assign instr = mem[addr[31:2]];

endmodule

// Bộ nhớ lệnh là word-addressable theo addr[31:2]
// Vì lệnh RISC-V RV32I dài 4 byte nên bỏ 2 bit thấp
// imem.hex là file chứa mã máy
// CPU dùng PC để lấy lệnh

pc_reg.v
module pc_reg (
    input  wire        clk,      // clock hệ thống
    input  wire        rst,      // reset
    input  wire [31:0] pc_next,  // giá trị PC kế tiếp
    output reg  [31:0] pc        // giá trị PC hiện tại
);

    // PC là một thanh ghi, cập nhật theo cạnh lên của clock
    always @(posedge clk or posedge rst) begin
        if (rst)
            pc <= 32'b0;     // khi reset, PC quay về địa chỉ 0
        else
            pc <= pc_next;   // nếu không reset, nhận giá trị PC mới
    end

endmodule
// pc là thanh ghi Program Counter
// Mỗi cạnh lên clock, PC nhận giá trị mới pc_next
// Khi reset thì PC về 0

top.v
module top (
    input wire clk,   // clock hệ thống
    input wire rst    // reset hệ thống
);

    // =========================
    // Khai báo dây tín hiệu nội bộ
    // =========================
    wire [31:0] pc, pc_next, pc_plus4;
    wire [31:0] instr;
    wire [31:0] imm;
    wire [31:0] rs1_data, rs2_data;
    wire [31:0] alu_a, alu_b, alu_y;
    wire [31:0] dmem_rdata;
    wire [31:0] wb_data;

    // Tín hiệu điều khiển
    wire        pc_sel;
    wire [2:0]  imm_sel;
    wire        reg_wen;
    wire        br_un;
    wire        br_eq;
    wire        br_lt;
    wire        b_sel;
    wire        a_sel;
    wire [3:0]  alu_sel;
    wire        mem_rw;
    wire [1:0]  wb_sel;

    // Tách địa chỉ thanh ghi từ instruction
    wire [4:0] rs1 = instr[19:15];
    wire [4:0] rs2 = instr[24:20];
    wire [4:0] rd  = instr[11:7];

    // Tính PC + 4
    assign pc_plus4 = pc + 32'd4;

    // =========================
    // Module PC
    // =========================
    pc_reg U_PC (
        .clk(clk),
        .rst(rst),
        .pc_next(pc_next),
        .pc(pc)
    );

    // =========================
    // Bộ nhớ lệnh
    // =========================
    imem U_IMEM (
        .addr(pc),
        .instr(instr)
    );

    // =========================
    // Register file
    // =========================
    reg_file U_RF (
        .clk(clk),
        .we(reg_wen),
        .rs1(rs1),
        .rs2(rs2),
        .rd(rd),
        .wd(wb_data),
        .rd1(rs1_data),
        .rd2(rs2_data)
    );

    // =========================
    // Immediate Generator
    // =========================
    imm_gen U_IMM (
        .instr(instr),
        .imm_sel(imm_sel),
        .imm(imm)
    );

    // =========================
    // Branch Comparator
    // =========================
    branch_comp U_BRC (
        .a(rs1_data),
        .b(rs2_data),
        .br_un(br_un),
        .br_eq(br_eq),
        .br_lt(br_lt)
    );

    // =========================
    // Control Unit
    // =========================
    control_unit U_CTRL (
        .instr(instr),
        .br_eq(br_eq),
        .br_lt(br_lt),
        .pc_sel(pc_sel),
        .imm_sel(imm_sel),
        .reg_wen(reg_wen),
        .br_un(br_un),
        .b_sel(b_sel),
        .a_sel(a_sel),
        .alu_sel(alu_sel),
        .mem_rw(mem_rw),
        .wb_sel(wb_sel)
    );

    // =========================
    // MUX chọn đầu vào cho ALU
    // =========================
    // Nếu a_sel = 1 thì ALU lấy PC
    // Nếu a_sel = 0 thì ALU lấy rs1_data
    assign alu_a = (a_sel) ? pc : rs1_data;

    // Nếu b_sel = 1 thì ALU lấy imm
    // Nếu b_sel = 0 thì ALU lấy rs2_data
    assign alu_b = (b_sel) ? imm : rs2_data;

    // =========================
    // ALU
    // =========================
    alu U_ALU (
        .a(alu_a),
        .b(alu_b),
        .alu_sel(alu_sel),
        .y(alu_y)
    );

    // =========================
    // Data memory
    // =========================
    dmem U_DMEM (
        .clk(clk),
        .we(mem_rw),
        .addr(alu_y),
        .wdata(rs2_data),
        .rdata(dmem_rdata)
    );

    // =========================
    // MUX write-back
    // Chọn dữ liệu ghi về thanh ghi
    // =========================
    assign wb_data = (wb_sel == 2'b00) ? dmem_rdata :
                     (wb_sel == 2'b01) ? alu_y :
                     (wb_sel == 2'b10) ? pc_plus4 :
                     32'b0;

    // =========================
    // Chọn PC kế tiếp
    // Nếu pc_sel = 0 -> PC + 4
    // Nếu pc_sel = 1 -> nhảy/branch đến alu_y
    // Riêng jalr: bit thấp nhất phải bằng 0
    // =========================
    assign pc_next = pc_sel ?
                     ((instr[6:0] == 7'b1100111) ? {alu_y[31:1], 1'b0} : alu_y)
                     : pc_plus4;

endmodule

// Đây là module top-level
// Nhiệm vụ:
// nối các module lại với nhau
// điều phối luồng dữ liệu
// cập nhật PC
// ghi dữ liệu về register file

tb_top.v
module tb_top;
    reg clk;   // clock mô phỏng
    reg rst;   // reset mô phỏng

    // Gọi module top-level cần test
    top dut (
        .clk(clk),
        .rst(rst)
    );

    // Tạo clock chu kỳ 10 time unit
    initial begin
        clk = 0;
        forever #5 clk = ~clk;
    end

    // Reset trong 20 time unit đầu
    initial begin
        rst = 1;
        #20;
        rst = 0;

        // Cho mô phỏng chạy thêm 300 time unit rồi dừng
        #300;
        $finish;
    end

    // Ghi sóng ra file wave.vcd để mở bằng GTKWave
    initial begin
        $dumpfile("wave.vcd");
        $dumpvars(0, tb_top);
    end

endmodule

//testbench cho top-level module, tạo clock và reset, chạy mô phỏng trong 300 time unit, và ghi lại sóng vào file wave.vcd để xem sau
//clock chu kỳ 10 đơn vị thời gian
//reset 20 đơn vị đầu
//xuất waveform để xem bằng GTKWave

wave.vcd
$date
	Fri Apr 10 08:13:23 2026
$end
$version
	Icarus Verilog
$end
$timescale
	1s
$end
$scope module tb_top $end
$var reg 1 ! clk $end
$var reg 1 " rst $end
$scope module dut $end
$var wire 1 ! clk $end
$var wire 1 " rst $end
$var wire 2 # wb_sel [1:0] $end
$var wire 32 $ wb_data [31:0] $end
$var wire 32 % rs2_data [31:0] $end
$var wire 5 & rs2 [4:0] $end
$var wire 32 ' rs1_data [31:0] $end
$var wire 5 ( rs1 [4:0] $end
$var wire 1 ) reg_wen $end
$var wire 5 * rd [4:0] $end
$var wire 1 + pc_sel $end
$var wire 32 , pc_plus4 [31:0] $end
$var wire 32 - pc_next [31:0] $end
$var wire 32 . pc [31:0] $end
$var wire 1 / mem_rw $end
$var wire 32 0 instr [31:0] $end
$var wire 3 1 imm_sel [2:0] $end
$var wire 32 2 imm [31:0] $end
$var wire 32 3 dmem_rdata [31:0] $end
$var wire 1 4 br_un $end
$var wire 1 5 br_lt $end
$var wire 1 6 br_eq $end
$var wire 1 7 b_sel $end
$var wire 32 8 alu_y [31:0] $end
$var wire 4 9 alu_sel [3:0] $end
$var wire 32 : alu_b [31:0] $end
$var wire 32 ; alu_a [31:0] $end
$var wire 1 < a_sel $end
$scope module U_ALU $end
$var wire 32 = a [31:0] $end
$var wire 32 > b [31:0] $end
$var wire 4 ? alu_sel [3:0] $end
$var reg 32 @ y [31:0] $end
$upscope $end
$scope module U_BRC $end
$var wire 1 4 br_un $end
$var wire 1 5 br_lt $end
$var wire 1 6 br_eq $end
$var wire 32 A b [31:0] $end
$var wire 32 B a [31:0] $end
$upscope $end
$scope module U_CTRL $end
$var wire 1 6 br_eq $end
$var wire 1 5 br_lt $end
$var wire 7 C opcode [6:0] $end
$var wire 32 D instr [31:0] $end
$var wire 7 E funct7 [6:0] $end
$var wire 3 F funct3 [2:0] $end
$var parameter 4 G ALU_ADD $end
$var parameter 4 H ALU_AND $end
$var parameter 4 I ALU_OR $end
$var parameter 4 J ALU_SLL $end
$var parameter 4 K ALU_SLT $end
$var parameter 4 L ALU_SLTU $end
$var parameter 4 M ALU_SRA $end
$var parameter 4 N ALU_SRL $end
$var parameter 4 O ALU_SUB $end
$var parameter 4 P ALU_XOR $end
$var parameter 3 Q IMM_B $end
$var parameter 3 R IMM_I $end
$var parameter 3 S IMM_J $end
$var parameter 3 T IMM_S $end
$var parameter 3 U IMM_U $end
$var parameter 2 V WB_ALU $end
$var parameter 2 W WB_MEM $end
$var parameter 2 X WB_PC4 $end
$var reg 1 < a_sel $end
$var reg 4 Y alu_sel [3:0] $end
$var reg 1 7 b_sel $end
$var reg 1 4 br_un $end
$var reg 3 Z imm_sel [2:0] $end
$var reg 1 / mem_rw $end
$var reg 1 + pc_sel $end
$var reg 1 ) reg_wen $end
$var reg 2 [ wb_sel [1:0] $end
$upscope $end
$scope module U_DMEM $end
$var wire 32 \ addr [31:0] $end
$var wire 1 ! clk $end
$var wire 32 ] rdata [31:0] $end
$var wire 1 / we $end
$var wire 32 ^ wdata [31:0] $end
$upscope $end
$scope module U_IMEM $end
$var wire 32 _ instr [31:0] $end
$var wire 32 ` addr [31:0] $end
$upscope $end
$scope module U_IMM $end
$var wire 3 a imm_sel [2:0] $end
$var wire 32 b instr [31:0] $end
$var reg 32 c imm [31:0] $end
$upscope $end
$scope module U_PC $end
$var wire 1 ! clk $end
$var wire 32 d pc_next [31:0] $end
$var wire 1 " rst $end
$var reg 32 e pc [31:0] $end
$upscope $end
$scope module U_RF $end
$var wire 1 ! clk $end
$var wire 5 f rd [4:0] $end
$var wire 5 g rs1 [4:0] $end
$var wire 5 h rs2 [4:0] $end
$var wire 32 i wd [31:0] $end
$var wire 1 ) we $end
$var wire 32 j rd2 [31:0] $end
$var wire 32 k rd1 [31:0] $end
$var integer 32 l i [31:0] $end
$upscope $end
$upscope $end
$upscope $end
$enddefinitions $end
$comment Show the parameter values. $end
$dumpall
b10 X
b0 W
b1 V
b11 U
b1 T
b100 S
b0 R
b10 Q
b100 P
b1 O
b1000 N
b1001 M
b110 L
b101 K
b111 J
b11 I
b10 H
b0 G
$end
#0
$dumpvars
b100000 l
b0 k
b0 j
b101 i
b101 h
b0 g
b1 f
b0 e
b100 d
b101 c
b10100000000000010010011 b
b0 a
b0 `
b10100000000000010010011 _
b0 ^
bx ]
b101 \
b1 [
b0 Z
b0 Y
b0 F
b0 E
b10100000000000010010011 D
b10011 C
b0 B
b0 A
b101 @
b0 ?
b101 >
b0 =
0<
b0 ;
b101 :
b0 9
b101 8
17
16
05
04
bx 3
b101 2
b0 1
b10100000000000010010011 0
0/
b0 .
b100 -
b100 ,
0+
b1 *
1)
b0 (
b0 '
b101 &
b0 %
b101 $
b1 #
1"
0!
$end
#5
1!
#10
0!
#15
1!
#20
0!
0"
#25
b111 $
b111 i
b111 8
b111 @
b111 \
b111 :
b111 >
b10 *
b10 f
b111 &
b111 h
b111 2
b111 c
b11100000000000100010011 0
b11100000000000100010011 D
b11100000000000100010011 _
b11100000000000100010011 b
b1000 -
b1000 d
b1000 ,
b100 .
b100 `
b100 e
1!
#30
0!
#35
b1100 $
b1100 i
15
b101 ;
b101 =
b1100 8
b1100 @
b1100 \
07
1)
b111 %
b111 A
b111 ^
b111 j
06
b101 '
b101 B
b101 k
b111 :
b111 >
b110011 C
b11 *
b11 f
b10 &
b10 h
b1 (
b1 g
b10 2
b10 c
b1000001000000110110011 0
b1000001000000110110011 D
b1000001000000110110011 _
b1000001000000110110011 b
b1100 -
b1100 d
b1100 ,
b1000 .
b1000 `
b1000 e
1!
#40
0!
#45
bx $
bx i
bx 8
bx @
bx \
bx :
bx >
x5
bx ;
bx =
0)
bx %
bx A
bx ^
bx j
x6
bx '
bx B
bx k
bx E
bx F
bx C
bx *
bx f
bx &
bx h
bx (
bx g
bx 2
bx c
bx 0
bx D
bx _
bx b
b10000 -
b10000 d
b10000 ,
b1100 .
b1100 `
b1100 e
1!
#50
0!
#55
b10100 -
b10100 d
b10100 ,
b10000 .
b10000 `
b10000 e
1!
#60
0!
#65
b11000 -
b11000 d
b11000 ,
b10100 .
b10100 `
b10100 e
1!
#70
0!
#75
b11100 -
b11100 d
b11100 ,
b11000 .
b11000 `
b11000 e
1!
#80
0!
#85
b100000 -
b100000 d
b100000 ,
b11100 .
b11100 `
b11100 e
1!
#90
0!
#95
b100100 -
b100100 d
b100100 ,
b100000 .
b100000 `
b100000 e
1!
#100
0!
#105
b101000 -
b101000 d
b101000 ,
b100100 .
b100100 `
b100100 e
1!
#110
0!
#115
b101100 -
b101100 d
b101100 ,
b101000 .
b101000 `
b101000 e
1!
#120
0!
#125
b110000 -
b110000 d
b110000 ,
b101100 .
b101100 `
b101100 e
1!
#130
0!
#135
b110100 -
b110100 d
b110100 ,
b110000 .
b110000 `
b110000 e
1!
#140
0!
#145
b111000 -
b111000 d
b111000 ,
b110100 .
b110100 `
b110100 e
1!
#150
0!
#155
b111100 -
b111100 d
b111100 ,
b111000 .
b111000 `
b111000 e
1!
#160
0!
#165
b1000000 -
b1000000 d
b1000000 ,
b111100 .
b111100 `
b111100 e
1!
#170
0!
#175
b1000100 -
b1000100 d
b1000100 ,
b1000000 .
b1000000 `
b1000000 e
1!
#180
0!
#185
b1001000 -
b1001000 d
b1001000 ,
b1000100 .
b1000100 `
b1000100 e
1!
#190
0!
#195
b1001100 -
b1001100 d
b1001100 ,
b1001000 .
b1001000 `
b1001000 e
1!
#200
0!
#205
b1010000 -
b1010000 d
b1010000 ,
b1001100 .
b1001100 `
b1001100 e
1!
#210
0!
#215
b1010100 -
b1010100 d
b1010100 ,
b1010000 .
b1010000 `
b1010000 e
1!
#220
0!
#225
b1011000 -
b1011000 d
b1011000 ,
b1010100 .
b1010100 `
b1010100 e
1!
#230
0!
#235
b1011100 -
b1011100 d
b1011100 ,
b1011000 .
b1011000 `
b1011000 e
1!
#240
0!
#245
b1100000 -
b1100000 d
b1100000 ,
b1011100 .
b1011100 `
b1011100 e
1!
#250
0!
#255
b1100100 -
b1100100 d
b1100100 ,
b1100000 .
b1100000 `
b1100000 e
1!
#260
0!
#265
b1101000 -
b1101000 d
b1101000 ,
b1100100 .
b1100100 `
b1100100 e
1!
#270
0!
#275
b1101100 -
b1101100 d
b1101100 ,
b1101000 .
b1101000 `
b1101000 e
1!
#280
0!
#285
b1110000 -
b1110000 d
b1110000 ,
b1101100 .
b1101100 `
b1101100 e
1!
#290
0!
#295
b1110100 -
b1110100 d
b1110100 ,
b1110000 .
b1110000 `
b1110000 e
1!
#300
0!
#305
b1111000 -
b1111000 d
b1111000 ,
b1110100 .
b1110100 `
b1110100 e
1!
#310
0!
#315
b1111100 -
b1111100 d
b1111100 ,
b1111000 .
b1111000 `
b1111000 e
1!
